pysignora/__init__.py
pysignora/makegps.py
pysignora/signora.py
pysignora/version.py
pysignora-0.1.1.dist-info/LICENSE
pysignora-0.1.1.dist-info/METADATA
pysignora-0.1.1.dist-info/WHEEL
pysignora-0.1.1.dist-info/top_level.txt
pysignora-0.1.1.dist-info/RECORD
