Metadata-Version: 2.1
Name: pysignora
Version: 0.1.1
Summary: Pathway gene-pair signature overrepresentation analysis
Home-page: https://github.com/veghp/pySignora
Author: Peter Vegh
License: GPLv3+
Keywords: biology
Platform: UNKNOWN
Classifier: Programming Language :: Python :: 3
Classifier: License :: OSI Approved :: GNU General Public License v3 or later (GPLv3+)
Classifier: Operating System :: OS Independent
